network_prog_it19/__init__.py
network_prog_it19/client.py
network_prog_it19/datetime_py.py
network_prog_it19/file_read.py
network_prog_it19/python_arg_py.py
network_prog_it19/requests_net.py
network_prog_it19/restful_net.py
network_prog_it19/server_restful.py
network_prog_it19/sqlite_net.py
network_prog_it19/tcp_net.py
network_prog_it19/tcp_udp_rest_sqltie.py
network_prog_it19/udp_net.py
network_prog_it19/src/__init__.py
network_prog_it19/src/Displayers/__init__.py
network_prog_it19/src/Displayers/displayer.py
network_prog_it19/src/Globals/__init__.py
network_prog_it19/src/Globals/connectionData.py
network_prog_it19/src/Globals/globalConsts.py
network_prog_it19/src/Processers/__init__.py
network_prog_it19/src/Processers/processor.py
network_prog_it19/src_server/__init__.py
network_prog_it19/src_server/Configurator/__init__.py
network_prog_it19/src_server/Configurator/mainConfiguration.py
network_prog_it19/src_server/DatabaseManager/__init__.py
network_prog_it19/src_server/DatabaseManager/redisController.py
network_prog_it19/src_server/Globals/__init__.py
network_prog_it19/src_server/Globals/globalConsts.py
network_prog_it19/src_server/Helpers/__init__.py
network_prog_it19/src_server/Helpers/endpointBuilder.py
network_prog_it19/src_server/Helpers/parser.py
network_prog_it19/src_server/ResourceControllers/__init__.py
network_prog_it19/src_server/ResourceControllers/authController.py
network_prog_it19/src_server/ResourceControllers/portController.py
network_prog_it19-0.0.9.dist-info/METADATA
network_prog_it19-0.0.9.dist-info/WHEEL
network_prog_it19-0.0.9.dist-info/top_level.txt
network_prog_it19-0.0.9.dist-info/RECORD
